antinex_client/__init__.py
antinex_client/ai_client.py
antinex_client/build_ai_client_from_env.py
antinex_client/consts.py
antinex_client/generate_ai_request.py
antinex_client/utils.py
antinex_client/log/__init__.py
antinex_client/log/setup_logging.py
antinex_client/scripts/__init__.py
antinex_client/scripts/ai_env_predict.py
antinex_client/scripts/ai_get_job.py
antinex_client/scripts/ai_get_prepared_dataset.py
antinex_client/scripts/ai_get_results.py
antinex_client/scripts/ai_prepare_dataset.py
antinex_client/scripts/ai_train_dnn.py
antinex_client-1.3.6.data/scripts/ai
antinex_client-1.3.6.data/scripts/ai_env_predict.py
antinex_client-1.3.6.data/scripts/ai_get_job.py
antinex_client-1.3.6.data/scripts/ai_get_prepared_dataset.py
antinex_client-1.3.6.data/scripts/ai_get_results.py
antinex_client-1.3.6.data/scripts/ai_prepare_dataset.py
antinex_client-1.3.6.data/scripts/ai_train_dnn.py
antinex_client-1.3.6.dist-info/LICENSE
antinex_client-1.3.6.dist-info/METADATA
antinex_client-1.3.6.dist-info/WHEEL
antinex_client-1.3.6.dist-info/top_level.txt
antinex_client-1.3.6.dist-info/RECORD
