Metadata-Version: 2.1
Name: antinex-client
Version: 1.3.6
Summary: AntiNex Python client
Home-page: https://github.com/jay-johnson/antinex-client
Author: Jay Johnson
Author-email: jay.p.h.johnson@gmail.com
License: UNKNOWN
Platform: UNKNOWN
Classifier: Development Status :: 5 - Production/Stable
Classifier: Intended Audience :: Developers
Classifier: License :: OSI Approved :: Apache Software License
Classifier: Operating System :: OS Independent
Classifier: Programming Language :: Python :: 3.5
Classifier: Programming Language :: Python :: 3.6
Classifier: Programming Language :: Python :: Implementation :: PyPy
Classifier: Topic :: Software Development :: Libraries :: Python Modules
Requires-Dist: colorlog
Requires-Dist: coverage
Requires-Dist: flake8
Requires-Dist: matplotlib
Requires-Dist: numpy
Requires-Dist: pandas
Requires-Dist: pep8
Requires-Dist: pipenv
Requires-Dist: pycodestyle
Requires-Dist: pylint
Requires-Dist: recommonmark
Requires-Dist: requests
Requires-Dist: seaborn
Requires-Dist: sphinx
Requires-Dist: sphinx-autobuild
Requires-Dist: sphinx-rtd-theme
Requires-Dist: spylunking
Requires-Dist: tox
Requires-Dist: tqdm
Requires-Dist: unittest2
Requires-Dist: mock
